{
  "project_info": {
    "project_number": "11571882694",
    "firebase_url": "https://aych-fanni.firebaseio.com",
    "project_id": "aych-fanni",
    "storage_bucket": "aych-fanni.appspot.com"
  },
  "client": [
    {
      "client_info": {
        "mobilesdk_app_id": "1:11571882694:android:554695853c4c00d4",
        "android_client_info": {
          "package_name": "com.example.nourelhoudazribi.aaychfanni"
        }
      },
      "oauth_client": [
        {
          "client_id": "11571882694-vp36g15n8ph7vkdk6lo6srhh412c34to.apps.googleusercontent.com",
          "client_type": 1,
          "android_info": {
            "package_name": "com.example.nourelhoudazribi.aaychfanni",
            "certificate_hash": "b45ab9c3bc574046243386e44d68f1becf7d3e93"
          }
        },
        {
          "client_id": "11571882694-9nkk7j14ljbmm2r2ijll4rufohvt9b08.apps.googleusercontent.com",
          "client_type": 3
        }
      ],
      "api_key": [
        {
          "current_key": "AIzaSyArjljOLxo2OwpYsxEZiu8t-U3tJh4T_is"
        }
      ],
      "services": {
        "analytics_service": {
          "status": 1
        },
        "appinvite_service": {
          "status": 2,
          "other_platform_oauth_client": [
            {
              "client_id": "11571882694-9nkk7j14ljbmm2r2ijll4rufohvt9b08.apps.googleusercontent.com",
              "client_type": 3
            }
          ]
        },
        "ads_service": {
          "status": 2
        }
      }
    }
  ],
  "configuration_version": "1"
}